georgia/cli.py
georgia/scrap.py
georgia_broker-0.2.0.dist-info/METADATA
georgia_broker-0.2.0.dist-info/WHEEL
georgia_broker-0.2.0.dist-info/RECORD
